<annotation>
	<folder>bus</folder>
	<filename>bus_112.jpg</filename>
	<path>F:\test for car\bus\bus_112.jpg</path>
	<source>
		<database>Unknown</database>
	</source>
	<size>
		<width>1253</width>
		<height>687</height>
		<depth>3</depth>
	</size>
	<segmented>0</segmented>
	<object>
		<name>bus</name>
		<pose>Unspecified</pose>
		<truncated>0</truncated>
		<difficult>0</difficult>
		<bndbox>
			<xmin>82</xmin>
			<ymin>197</ymin>
			<xmax>925</xmax>
			<ymax>524</ymax>
		</bndbox>
	</object>
</annotation>
